{
  "voices": [
    {
      "amp": 0.06329750657938363,
      "ampLfoDepth": 1.5755624941266908,
      "ampLfoHz": 0.034505245495625565,
      "ampLfoSpeedModDepthHz": 4.712434038010526,
      "ampLfoSpeedModHz": 0.03396495822890742,
      "ampLfo2Hz": 0.07998882733296213,
      "ampLfo2Depth": 1.5898944663475023,
      "ampLfo2SpeedModDepthHz": 4.725213599862814,
      "ampLfo2SpeedModHz": 0.35,
      "fastAmpLfoHz": 5.437838513446887,
      "fastAmpLfoDepth": 1.2181279692001816,
      "fastAmpLfoSpeedModDepthHz": 1,
      "fastAmpLfoSpeedModHz": 0.04027985220489023,
      "panLfoHz": 0.024518100012743686,
      "panLfoDepth": 0.95,
      "note": -12
    },
    {
      "amp": 0.007890914656229342,
      "ampLfoDepth": 1.5213291916899736,
      "ampLfoHz": 0.04112548916615292,
      "ampLfoSpeedModDepthHz": 5,
      "ampLfoSpeedModHz": 0.03453246878378136,
      "ampLfo2Hz": 0.1017218171596969,
      "ampLfo2Depth": 1.6,
      "ampLfo2SpeedModDepthHz": 4.907974693972611,
      "ampLfo2SpeedModHz": 0.2332252908745137,
      "fastAmpLfoHz": 8.409436287116769,
      "fastAmpLfoDepth": 1.5547582717202486,
      "fastAmpLfoSpeedModDepthHz": 1,
      "fastAmpLfoSpeedModHz": 0.01980297114165973,
      "panLfoHz": 0.03096908467913855,
      "panLfoDepth": 0.85,
      "note": -5.162647857022417,
      "carrierDetuneRatio": 1.0145453349375237
    },
    {
      "amp": 0.05680643386875894,
      "ampLfoDepth": 1.5457406448864925,
      "ampLfoHz": 0.022518481677100133,
      "ampLfoSpeedModDepthHz": 4.8731716426958265,
      "ampLfoSpeedModHz": 0.03391584320012808,
      "ampLfo2Hz": 0.1665363947681568,
      "ampLfo2Depth": 1.559311052430261,
      "ampLfo2SpeedModDepthHz": 4.885945228530547,
      "ampLfo2SpeedModHz": 0.17525773960139354,
      "fastAmpLfoHz": 6.770278065412213,
      "fastAmpLfoDepth": 0.6392977675231326,
      "fastAmpLfoSpeedModDepthHz": 1,
      "fastAmpLfoSpeedModHz": 0.0188764439977799,
      "panLfoHz": 0.047412177564131644,
      "panLfoDepth": 0.9406560819134245,
      "note": -22
    },
    {
      "amp": 0.05851958866208316,
      "ampLfoDepth": 1.4954552168552973,
      "ampLfoHz": 0.031155103464553306,
      "ampLfoSpeedModDepthHz": 4.808770355002203,
      "ampLfoSpeedModHz": 0.028361574343592235,
      "ampLfo2Hz": 0.13042267982505862,
      "ampLfo2Depth": 1.6,
      "ampLfo2SpeedModDepthHz": 5,
      "ampLfo2SpeedModHz": 0.29071745123912046,
      "fastAmpLfoHz": 4.199421382271395,
      "fastAmpLfoDepth": 0.6434147764355403,
      "fastAmpLfoSpeedModDepthHz": 1,
      "fastAmpLfoSpeedModHz": 0.029309326770902543,
      "panLfoHz": 0.05,
      "panLfoDepth": 0.9024484554211256,
      "note": -12
    },
    {
      "amp": 0.061968343269375226,
      "ampLfoDepth": 1.515723474737527,
      "ampLfoHz": 0.015496807065834044,
      "ampLfoSpeedModDepthHz": 5,
      "ampLfoSpeedModHz": 0.02,
      "ampLfo2Hz": 0.1653505531342328,
      "ampLfo2Depth": 1.534218076379555,
      "ampLfo2SpeedModDepthHz": 5,
      "ampLfo2SpeedModHz": 0.32613275830912897,
      "fastAmpLfoHz": 4.658853881477107,
      "fastAmpLfoDepth": 0.5556686661836279,
      "fastAmpLfoSpeedModDepthHz": 1,
      "fastAmpLfoSpeedModHz": 0.023473888828370572,
      "panLfoHz": 0.05,
      "panLfoDepth": 0.9429049681038374,
      "note": -16
    },
    {
      "amp": 0.06178080374949631,
      "ampLfoDepth": 1.557515229583709,
      "ampLfoHz": 0.040379951428052764,
      "ampLfoSpeedModDepthHz": 4.738454353166384,
      "ampLfoSpeedModHz": 0.04867527517621611,
      "ampLfo2Hz": 0.06130602892428214,
      "ampLfo2Depth": 1.6,
      "ampLfo2SpeedModDepthHz": 5,
      "ampLfo2SpeedModHz": 0.35,
      "fastAmpLfoHz": 10.320994537977747,
      "fastAmpLfoDepth": 0.16874883282547126,
      "fastAmpLfoSpeedModDepthHz": 1,
      "fastAmpLfoSpeedModHz": 0.04037683071612377,
      "panLfoHz": 0.031222485335393804,
      "panLfoDepth": 0.9037583684615693,
      "note": -14
    },
    {
      "amp": 0.062469725972639806,
      "ampLfoDepth": 1.5809426937304758,
      "ampLfoHz": 0.026645730265931346,
      "ampLfoSpeedModDepthHz": 4.960994805689201,
      "ampLfoSpeedModHz": 0.024348325707321518,
      "ampLfo2Hz": 0.15739510104998172,
      "ampLfo2Depth": 1.6,
      "ampLfo2SpeedModDepthHz": 4.776345617202191,
      "ampLfo2SpeedModHz": 0.28628012870575104,
      "fastAmpLfoHz": 9.89177600649446,
      "fastAmpLfoDepth": 0.35005546317128644,
      "fastAmpLfoSpeedModDepthHz": 1,
      "fastAmpLfoSpeedModHz": 0.040380080460309616,
      "panLfoHz": 0.04955278104571711,
      "panLfoDepth": 0.95,
      "note": -20
    },
    {
      "amp": 0.05870642674798295,
      "ampLfoDepth": 1.492223336906471,
      "ampLfoHz": 0.03164879792962336,
      "ampLfoSpeedModDepthHz": 4.9655929986074545,
      "ampLfoSpeedModHz": 0.040464998118511494,
      "ampLfo2Hz": 0.11676040686185997,
      "ampLfo2Depth": 1.5626740585311023,
      "ampLfo2SpeedModDepthHz": 5,
      "ampLfo2SpeedModHz": 0.2552287259548553,
      "fastAmpLfoHz": 7.578618964275538,
      "fastAmpLfoDepth": 0.019952100708510036,
      "fastAmpLfoSpeedModDepthHz": 1,
      "fastAmpLfoSpeedModHz": 0.04115987972241023,
      "panLfoHz": 0.0391955595737774,
      "panLfoDepth": 0.9089827550165315,
      "note": -7
    },
    {
      "amp": 0.05978430586049433,
      "ampLfoDepth": 1.6,
      "ampLfoHz": 0.041504409508936795,
      "ampLfoSpeedModDepthHz": 4.769551445839356,
      "ampLfoSpeedModHz": 0.02937380648070023,
      "ampLfo2Hz": 0.06217351559317688,
      "ampLfo2Depth": 1.5314916792445565,
      "ampLfo2SpeedModDepthHz": 5,
      "ampLfo2SpeedModHz": 0.34565190643289434,
      "fastAmpLfoHz": 6.1661320047313195,
      "fastAmpLfoDepth": 0.8661413056371092,
      "fastAmpLfoSpeedModDepthHz": 1,
      "fastAmpLfoSpeedModHz": 0.021012487466902013,
      "panLfoHz": 0.025091090462449003,
      "panLfoDepth": 0.9292605768410164,
      "note": -19
    },
    {
      "amp": 0.058976075555355306,
      "ampLfoDepth": 1.5775652893470569,
      "ampLfoHz": 0.042539182218334304,
      "ampLfoSpeedModDepthHz": 4.78170092117081,
      "ampLfoSpeedModHz": 0.05182558821502385,
      "ampLfo2Hz": 0.13790191125076143,
      "ampLfo2Depth": 1.6,
      "ampLfo2SpeedModDepthHz": 4.989978805065616,
      "ampLfo2SpeedModHz": 0.35,
      "fastAmpLfoHz": 9.289006691410572,
      "fastAmpLfoDepth": 0.20939155990120525,
      "fastAmpLfoSpeedModDepthHz": 1,
      "fastAmpLfoSpeedModHz": 0.04045375384448674,
      "panLfoHz": 0.05,
      "panLfoDepth": 0.95,
      "note": -15
    },
    {
      "amp": 0.05711789055234238,
      "ampLfoDepth": 1.5745146068980531,
      "ampLfoHz": 0.014728743021660738,
      "ampLfoSpeedModDepthHz": 5,
      "ampLfoSpeedModHz": 0.03596952158503266,
      "ampLfo2Hz": 0.1455296570224833,
      "ampLfo2Depth": 1.5767467514315499,
      "ampLfo2SpeedModDepthHz": 4.897969916741822,
      "ampLfo2SpeedModHz": 0.35,
      "fastAmpLfoHz": 7.5241839584722605,
      "fastAmpLfoDepth": 0.81312526242704,
      "fastAmpLfoSpeedModDepthHz": 1,
      "fastAmpLfoSpeedModHz": 0.021905049937327337,
      "panLfoHz": 0.025482080705990527,
      "panLfoDepth": 0.9451020694202981,
      "note": -16
    },
    {
      "amp": 0.0625487323652135,
      "ampLfoDepth": 1.5811723130158475,
      "ampLfoHz": 0.04235742210645452,
      "ampLfoSpeedModDepthHz": 4.810377540092538,
      "ampLfoSpeedModHz": 0.02021699879917068,
      "ampLfo2Hz": 0.16344748884325508,
      "ampLfo2Depth": 1.6,
      "ampLfo2SpeedModDepthHz": 5,
      "ampLfo2SpeedModHz": 0.17019916131789017,
      "fastAmpLfoHz": 3.1150474908673806,
      "fastAmpLfoDepth": 0.7091294410049966,
      "fastAmpLfoSpeedModDepthHz": 1,
      "fastAmpLfoSpeedModHz": 0.021458351326793797,
      "panLfoHz": 0.05,
      "panLfoDepth": 0.95,
      "note": -12
    }
  ],
  "voiceMacros": {
    "amp": 0.06,
    "ampLfoDepth": 1.5598891126271077,
    "ampLfoHz": 0.028578673858795936,
    "ampLfoSpeedModDepthHz": 5,
    "ampLfoSpeedModHz": 0.035,
    "ampLfo2Hz": 0.10961219979208248,
    "ampLfo2Depth": 1.6,
    "ampLfo2SpeedModDepthHz": 5,
    "ampLfo2SpeedModHz": 0.35,
    "tremoloDepth": 1.6,
    "tremoloBaseHz": 6,
    "tremoloDesyncWidth": 0.6,
    "tremoloDepthJitterHz": 0.006,
    "tremoloDepthJitterRateJitterDepth": 0.5,
    "tremoloDepthJitterRateJitterHz": 0.0386,
    "tremoloRateJitterDepth": 0.5,
    "tremoloRateJitterHz": 0.029,
    "tremoloRateJitterMorphDepth": 0.43,
    "tremoloRateJitterMorphHz": 0.0041,
    "panLfoHz": 0.05,
    "panLfoDepth": 0.94,
    "noteOffset": -12,
    "noteJitterDepthSemitones": 1,
    "noteJitterHz": 0.0005880514219470793,
    "noteJitterMode": "sine",
    "noteJitterRateJitterDepth": 0.16,
    "noteJitterRateJitterHz": 0.002,
    "noteJitterRateJitterMode": "sine",
    "rateJitterDepth": 0.5,
    "rateJitterHz": 0.002058787182336707,
    "rateJitterMode": "sine",
    "phraseRateHz": 0.000011263896987889249,
    "phraseRateJitterDepth": 0.28,
    "phraseRateJitterHz": 0.002,
    "phraseRateJitterMode": "sine",
    "phraseAvgLengthSec": 1.2,
    "phraseDepth": 0.9
  },
  "voiceMacroJitterTimeSec": 12084.040800016952,
  "influenceRate": 0.15,
  "activityScale": 0.2,
  "minVoices": 1,
  "maxVoices": 12,
  "averageVoiceLifetimeSec": 4,
  "voiceLifetimeJitter": 1,
  "voxelWeight": 0.15,
  "satelliteWeight": 0.3,
  "voiceFadeInSec": 11.5,
  "voiceFadeOutSec": 3.75,
  "notePitchSlideBaseSec": 0.027,
  "notePitchSlideJitterSec": 0,
  "voicePitchSpread": 3,
  "voicePitchBandpassEnabled": true,
  "voicePitchBandpassCenterSemitones": 0,
  "voicePitchBandpassQ": 4.5,
  "scaleClampMode": "major",
  "scaleCycleEnabled": true,
  "scaleCycleIntervalSec": 393,
  "scaleCycleJitterSec": 108,
  "scaleCycleDirection": "fifths",
  "chorusMix": 0.38,
  "chorusRateHz": 0.45,
  "chorusDepthMs": 1,
  "chorusDelayBaseMs": 18,
  "busPreDrive": 0.35,
  "busLowPassHz": 80,
  "busLowPassQ": 2.6,
  "busLowPassLfoHz": 0.0001,
  "busLowPassLfoDepthHz": 7350,
  "busLowPassLfoSpeedModHz": 0.035,
  "busLowPassLfoSpeedModDepthHz": 0.12,
  "preReverbStereoDelayTimeMs": 1909,
  "preReverbStereoDelayFeedback": 0.62,
  "preReverbStereoDelayFeedbackJitterDepth": 0.14,
  "preReverbStereoDelayFeedbackJitterHz": 1e-8,
  "preReverbStereoDelayFeedbackJitterRandomness": 1,
  "preReverbStereoDelayHighpassHz": 782,
  "preReverbStereoDelayLowpassHz": 10780,
  "preReverbStereoDelayVolume": 0.72,
  "preReverbStereoDelay2TimeMs": 7470,
  "preReverbStereoDelay2Volume": 1,
  "preReverbStereoDelayRateJitterDepthMs": 993,
  "preReverbStereoDelayRateJitterSpeedHz": 1.7914445620910395e-8,
  "preReverbStereoDelayRateJitterRandomness": 0.26,
  "reverbMix": 0.66,
  "reverbWetTrim": 0.78,
  "reverbDecaySec": 10,
  "reverbIrDurationSec": 6,
  "reverbIrDecayPerSec": 0.4,
  "reverbPreDelayMs": 133,
  "reverbIrDecorrelate": 0.94,
  "reverbIrDamping": 0.98,
  "reverbIrEarlyDensity": 0.98,
  "reverbWetFeedbackMs": 115,
  "reverbWetFeedback": 0.76,
  "reverbConvolverNormalize": true,
  "busWetSaturatorAmount": 0.24,
  "reeseEnabled": true,
  "reeseSolo": false,
  "reeseVoiceIndex": 1,
  "reeseOrderAfterVoice": 2,
  "reesePitchSemitones": 0,
  "reesePitchVariationSemitones": 6,
  "reesePitchJitterHz": 0.0003,
  "reesePitchJitterRandomness": 0.8,
  "reeseSwellsRateHz": 0.0443,
  "reeseSwellsRandomness": 0.85,
  "reeseVolume": 0.85,
  "reeseWidth": 0.85,
  "reeseDetuneSemitones": 0.25,
  "reeseHighpassHz": 64,
  "reeseLowpassBaseHz": 80,
  "reeseLowpassEnvAttackSec": 1.7,
  "reeseLowpassEnvDecaySec": 8.25,
  "reeseLowpassEnvDepthHz": 18380,
  "reesePitchSlideSec": 0.2,
  "reeseSwellsDepth": 1,
  "reeseDrive": 0.25,
  "reeseLargeSwellRateHz": 0.0001,
  "reverbMixLfoDepth": 0.92,
  "reverbMixLfoHz": 0.001
}
